{
  "name": "Ally Heal",
  "icon": "soulforge:textures/ui/ability_icon/ally_heal.png",
  "category": "soulforge:kindness",
  "pages": [
    {
      "type": "soulforge:ability_info",
      "name": "Ally Heal",
      "icon": "ally_heal",
      "cost": "20 mana",
      "cooldown": "10 seconds",
      "lv": 1
    },
    {
      "type": "patchouli:text",
      "text": "Infuse an ally with Kindness energy, healing them over time. The healing will cancel if the target takes damage."
    }
  ],
  "sortnum": 0,
  "advancement": "soulforge:hidden/kindness/unlocked_ally_heal"
}