{
  "display": {
    "icon": {
      "item": "soulforge:patience_patience"
    },
    "title": {
      "translate": "advancements.soulforge.pure_patience.title"
    },
    "description": {
      "translate": "advancements.soulforge.pure_patience.description"
    },
    "frame": "goal",
    "show_toast": true,
    "announce_to_chat": true,
    "hidden": false
  },
  "parent": "soulforge:traits/any_pure",
  "criteria": {
    "traits": {
      "trigger": "soulforge:player_trait",
      "conditions": {
        "trait": "Patience",
        "pure": true
      }
    }
  }
}